gemini_agent/__init__.py
gemini_agent/agent.py
vertex_agent/__init__.py
vertex_agent/agent.py
vertex_agent/api_client.py
vertex_agent/debug_logger.py
vertex_agent/tool_processor.py
vertex_agent/tool_registry.py
vertex_agent/variable_manager.py
vertex_agent/vertext_routing/__init__.py
vertex_agent/vertext_routing/payload_operations.py
vertex_agent/vertext_routing/project_manager.py
vertex_agent/vertext_routing/router.py
vertex_agent/vertext_routing/router_memory.py
vertex_agent/vertext_routing/token_bucket/local_TB.py
vertex_agent/vertext_routing/token_bucket/redis_TB.py
gemini_agent_framework-1.0.0.dist-info/METADATA
gemini_agent_framework-1.0.0.dist-info/WHEEL
gemini_agent_framework-1.0.0.dist-info/licenses/LICENSE
gemini_agent_framework-1.0.0.dist-info/RECORD
