Metadata-Version: 2.4
Name: gemini-agent-framework
Version: 1.0.0
Summary: A framework for building agents that use Gemini's function calling capabilities
Project-URL: Homepage, https://github.com/m7mdony/gemini-agent-framework
Project-URL: Documentation, https://m7mdony.github.io/gemini-agent-framework
Project-URL: Repository, https://github.com/m7mdony/gemini-agent-framework.git
Project-URL: Issues, https://github.com/m7mdony/gemini-agent-framework/issues
Author-email: Mohamed Baathman <mohamed.baathman2001@gmail.com>
License-Expression: MIT
License-File: LICENSE
Classifier: Development Status :: 4 - Beta
Classifier: Intended Audience :: Developers
Classifier: License :: OSI Approved :: MIT License
Classifier: Programming Language :: Python :: 3
Classifier: Programming Language :: Python :: 3.8
Classifier: Programming Language :: Python :: 3.9
Classifier: Programming Language :: Python :: 3.10
Classifier: Programming Language :: Python :: 3.11
Classifier: Topic :: Software Development :: Libraries :: Python Modules
Requires-Python: >=3.8
Requires-Dist: google-auth>=2.37.0
Requires-Dist: python-dotenv>=1.0.0
Requires-Dist: requests>=2.31.0
Provides-Extra: dev
Requires-Dist: black>=23.0.0; extra == 'dev'
Requires-Dist: flake8>=6.0.0; extra == 'dev'
Requires-Dist: isort>=5.0.0; extra == 'dev'
Requires-Dist: mypy>=1.0.0; extra == 'dev'
Requires-Dist: pytest-cov>=4.0.0; extra == 'dev'
Requires-Dist: pytest>=7.0.0; extra == 'dev'
